[{"id":79951,"url":"http:\/\/publications.newberry.org\/transcription\/mms-transcribe\/api\/files\/79951","file_urls":{"original":"http:\/\/publications.newberry.org\/transcription\/mms-transcribe\/files\/original\/f6b5b21ca69af3ce641337d9ba4bf6f8.jpg","fullsize":"http:\/\/publications.newberry.org\/transcription\/mms-transcribe\/files\/fullsize\/f6b5b21ca69af3ce641337d9ba4bf6f8.jpg","thumbnail":"http:\/\/publications.newberry.org\/transcription\/mms-transcribe\/files\/thumbnails\/f6b5b21ca69af3ce641337d9ba4bf6f8.jpg","square_thumbnail":"http:\/\/publications.newberry.org\/transcription\/mms-transcribe\/files\/square_thumbnails\/f6b5b21ca69af3ce641337d9ba4bf6f8.jpg"},"added":"2018-10-02T20:01:32+00:00","modified":"2019-09-24T15:38:12+00:00","filename":"f6b5b21ca69af3ce641337d9ba4bf6f8.jpg","authentication":"7d2d38e48950a844d48ce0128ac0710b","has_derivative_image":true,"mime_type":"image\/jpeg","order":null,"original_filename":"dance_ms_olson_box_01_fl_005_001_001_o2.jpg","size":1129460,"stored":true,"type_os":"JPEG image data, JFIF standard 1.01","metadata":{"mime_type":"image\/jpeg","video":{"dataformat":"jpg","lossless":false,"bits_per_sample":24,"pixel_aspect_ratio":1,"resolution_x":2327,"resolution_y":3600,"compression_ratio":0.044941826226742},"comments":{"IPTCEnvelope":{"CodedCharacterSet":["\u001b%G"]},"IPTCApplication":{"ApplicationRecordVersion":["\u0004"],"DateCreated":["20161018"],"TimeCreated":["030155"],"CopyrightNotice":["The Newberry Library"]}},"comments_html":{"IPTCEnvelope":{"CodedCharacterSet":["\u001b%G"]},"IPTCApplication":{"ApplicationRecordVersion":["\u0004"],"DateCreated":["20161018"],"TimeCreated":["030155"],"CopyrightNotice":["The Newberry Library"]}},"iptc":{"comments":{"IPTCEnvelope":{"CodedCharacterSet":["\u001b%G"]},"IPTCApplication":{"ApplicationRecordVersion":["\u0000\u0004"],"DateCreated":["20161018"],"TimeCreated":["030155"],"CopyrightNotice":["The Newberry Library"]}},"encoding":"ISO-8859-1"},"jpg":{"exif":{"FILE":{"FileName":"f6b5b21ca69af3ce641337d9ba4bf6f8.jpg","FileDateTime":1538510492,"FileSize":1129460,"FileType":2,"MimeType":"image\/jpeg","SectionsFound":"ANY_TAG, IFD0, EXIF"},"COMPUTED":{"html":"width=\"2327\" height=\"3600\"","Height":3600,"Width":2327,"IsColor":1,"ByteOrderMotorola":0,"CCDWidth":"22mm","ApertureFNumber":"f\/7.1"},"IFD0":{"Make":"Canon","Model":"Canon EOS 5D Mark III","Software":"Adobe Photoshop CS6 (Windows)","DateTime":"2016:10:18 16:05:05","Exif_IFD_Pointer":152},"EXIF":{"ExposureTime":0.02,"FNumber":7.1,"ExposureProgram":1,"ISOSpeedRatings":400,"UndefinedTag:0x8830":2,"UndefinedTag:0x8832":400,"ExifVersion":230,"DateTimeOriginal":"2016:10:18 03:01:55","DateTimeDigitized":"2016:10:18 03:01:55","ShutterSpeedValue":5.643856,"ApertureValue":5.655638,"ExposureBiasValue":0,"MaxApertureValue":3,"MeteringMode":5,"Flash":16,"FocalLength":42,"SubSecTimeOriginal":34,"ColorSpace":65535,"ExifImageWidth":3525,"ExifImageLength":5453,"FocalPlaneXResolution":1600,"FocalPlaneYResolution":1600,"FocalPlaneResolutionUnit":3,"CustomRendered":0,"ExposureMode":1,"WhiteBalance":1,"SceneCaptureType":0,"UndefinedTag:0xA431":358023000687,"UndefinedTag:0xA432":["28\/1","75\/1","0\/0","0\/0"],"UndefinedTag:0xA434":"28-75mm","UndefinedTag:0xA435":0}}}},"item":{"id":1138,"url":"http:\/\/publications.newberry.org\/transcription\/mms-transcribe\/api\/items\/1138","resource":"items"},"element_texts":[],"extended_resources":[]},{"id":79952,"url":"http:\/\/publications.newberry.org\/transcription\/mms-transcribe\/api\/files\/79952","file_urls":{"original":"http:\/\/publications.newberry.org\/transcription\/mms-transcribe\/files\/original\/7be4f2f4d72cd2b925453f0988de2c1f.jpg","fullsize":"http:\/\/publications.newberry.org\/transcription\/mms-transcribe\/files\/fullsize\/7be4f2f4d72cd2b925453f0988de2c1f.jpg","thumbnail":"http:\/\/publications.newberry.org\/transcription\/mms-transcribe\/files\/thumbnails\/7be4f2f4d72cd2b925453f0988de2c1f.jpg","square_thumbnail":"http:\/\/publications.newberry.org\/transcription\/mms-transcribe\/files\/square_thumbnails\/7be4f2f4d72cd2b925453f0988de2c1f.jpg"},"added":"2018-10-02T20:01:33+00:00","modified":"2019-09-24T15:38:12+00:00","filename":"7be4f2f4d72cd2b925453f0988de2c1f.jpg","authentication":"57d69376de4f7779ab6e088ca1e8fb4b","has_derivative_image":true,"mime_type":"image\/jpeg","order":null,"original_filename":"dance_ms_olson_box_01_fl_005_001_002_o2.jpg","size":884255,"stored":true,"type_os":"JPEG image data, JFIF standard 1.01","metadata":{"mime_type":"image\/jpeg","video":{"dataformat":"jpg","lossless":false,"bits_per_sample":24,"pixel_aspect_ratio":1,"resolution_x":2266,"resolution_y":3600,"compression_ratio":0.036132154882155},"comments":{"IPTCEnvelope":{"CodedCharacterSet":["\u001b%G"]},"IPTCApplication":{"ApplicationRecordVersion":["\u0004"],"DateCreated":["20161018"],"TimeCreated":["030200"],"CopyrightNotice":["The Newberry Library"]}},"comments_html":{"IPTCEnvelope":{"CodedCharacterSet":["\u001b%G"]},"IPTCApplication":{"ApplicationRecordVersion":["\u0004"],"DateCreated":["20161018"],"TimeCreated":["030200"],"CopyrightNotice":["The Newberry Library"]}},"iptc":{"comments":{"IPTCEnvelope":{"CodedCharacterSet":["\u001b%G"]},"IPTCApplication":{"ApplicationRecordVersion":["\u0000\u0004"],"DateCreated":["20161018"],"TimeCreated":["030200"],"CopyrightNotice":["The Newberry Library"]}},"encoding":"ISO-8859-1"},"jpg":{"exif":{"FILE":{"FileName":"7be4f2f4d72cd2b925453f0988de2c1f.jpg","FileDateTime":1538510492,"FileSize":884255,"FileType":2,"MimeType":"image\/jpeg","SectionsFound":"ANY_TAG, IFD0, EXIF"},"COMPUTED":{"html":"width=\"2266\" height=\"3600\"","Height":3600,"Width":2266,"IsColor":1,"ByteOrderMotorola":0,"CCDWidth":"21mm","ApertureFNumber":"f\/7.1"},"IFD0":{"Make":"Canon","Model":"Canon EOS 5D Mark III","Software":"Adobe Photoshop CS6 (Windows)","DateTime":"2016:10:18 16:03:20","Exif_IFD_Pointer":152},"EXIF":{"ExposureTime":0.02,"FNumber":7.1,"ExposureProgram":1,"ISOSpeedRatings":400,"UndefinedTag:0x8830":2,"UndefinedTag:0x8832":400,"ExifVersion":230,"DateTimeOriginal":"2016:10:18 03:02:00","DateTimeDigitized":"2016:10:18 03:02:00","ShutterSpeedValue":5.643856,"ApertureValue":5.655638,"ExposureBiasValue":0,"MaxApertureValue":3,"MeteringMode":5,"Flash":16,"FocalLength":42,"SubSecTimeOriginal":4,"ColorSpace":65535,"ExifImageWidth":3460,"ExifImageLength":5495,"FocalPlaneXResolution":1600,"FocalPlaneYResolution":1600,"FocalPlaneResolutionUnit":3,"CustomRendered":0,"ExposureMode":1,"WhiteBalance":1,"SceneCaptureType":0,"UndefinedTag:0xA431":358023000687,"UndefinedTag:0xA432":["28\/1","75\/1","0\/0","0\/0"],"UndefinedTag:0xA434":"28-75mm","UndefinedTag:0xA435":0}}}},"item":{"id":1138,"url":"http:\/\/publications.newberry.org\/transcription\/mms-transcribe\/api\/items\/1138","resource":"items"},"element_texts":[],"extended_resources":[]},{"id":79953,"url":"http:\/\/publications.newberry.org\/transcription\/mms-transcribe\/api\/files\/79953","file_urls":{"original":"http:\/\/publications.newberry.org\/transcription\/mms-transcribe\/files\/original\/cde40badfc50ec16d797fbd2417c7ddc.jpg","fullsize":"http:\/\/publications.newberry.org\/transcription\/mms-transcribe\/files\/fullsize\/cde40badfc50ec16d797fbd2417c7ddc.jpg","thumbnail":"http:\/\/publications.newberry.org\/transcription\/mms-transcribe\/files\/thumbnails\/cde40badfc50ec16d797fbd2417c7ddc.jpg","square_thumbnail":"http:\/\/publications.newberry.org\/transcription\/mms-transcribe\/files\/square_thumbnails\/cde40badfc50ec16d797fbd2417c7ddc.jpg"},"added":"2018-10-02T20:01:34+00:00","modified":"2019-09-24T15:38:12+00:00","filename":"cde40badfc50ec16d797fbd2417c7ddc.jpg","authentication":"cbeefa04af97ef51d023b815aac64ad6","has_derivative_image":true,"mime_type":"image\/jpeg","order":null,"original_filename":"dance_ms_olson_box_01_fl_005_002_001_o2.jpg","size":1513678,"stored":true,"type_os":"JPEG image data, JFIF standard 1.01","metadata":{"mime_type":"image\/jpeg","video":{"dataformat":"jpg","lossless":false,"bits_per_sample":24,"pixel_aspect_ratio":1,"resolution_x":2906,"resolution_y":3600,"compression_ratio":0.048229652570671},"comments":{"IPTCEnvelope":{"CodedCharacterSet":["\u001b%G"]},"IPTCApplication":{"ApplicationRecordVersion":["\u0004"],"DateCreated":["20161018"],"TimeCreated":["030215"],"CopyrightNotice":["The Newberry Library"]}},"comments_html":{"IPTCEnvelope":{"CodedCharacterSet":["\u001b%G"]},"IPTCApplication":{"ApplicationRecordVersion":["\u0004"],"DateCreated":["20161018"],"TimeCreated":["030215"],"CopyrightNotice":["The Newberry Library"]}},"iptc":{"comments":{"IPTCEnvelope":{"CodedCharacterSet":["\u001b%G"]},"IPTCApplication":{"ApplicationRecordVersion":["\u0000\u0004"],"DateCreated":["20161018"],"TimeCreated":["030215"],"CopyrightNotice":["The Newberry Library"]}},"encoding":"ISO-8859-1"},"jpg":{"exif":{"FILE":{"FileName":"cde40badfc50ec16d797fbd2417c7ddc.jpg","FileDateTime":1538510492,"FileSize":1513678,"FileType":2,"MimeType":"image\/jpeg","SectionsFound":"ANY_TAG, IFD0, EXIF"},"COMPUTED":{"html":"width=\"2906\" height=\"3600\"","Height":3600,"Width":2906,"IsColor":1,"ByteOrderMotorola":0,"CCDWidth":"21mm","ApertureFNumber":"f\/7.1"},"IFD0":{"Make":"Canon","Model":"Canon EOS 5D Mark III","Software":"Adobe Photoshop CS6 (Windows)","DateTime":"2016:10:18 16:02:02","Exif_IFD_Pointer":152},"EXIF":{"ExposureTime":0.02,"FNumber":7.1,"ExposureProgram":1,"ISOSpeedRatings":400,"UndefinedTag:0x8830":2,"UndefinedTag:0x8832":400,"ExifVersion":230,"DateTimeOriginal":"2016:10:18 03:02:15","DateTimeDigitized":"2016:10:18 03:02:15","ShutterSpeedValue":5.643856,"ApertureValue":5.655638,"ExposureBiasValue":0,"MaxApertureValue":3,"MeteringMode":5,"Flash":16,"FocalLength":38,"ColorSpace":65535,"ExifImageWidth":3424,"ExifImageLength":4241,"FocalPlaneXResolution":1600,"FocalPlaneYResolution":1600,"FocalPlaneResolutionUnit":3,"CustomRendered":0,"ExposureMode":1,"WhiteBalance":1,"SceneCaptureType":0,"UndefinedTag:0xA431":358023000687,"UndefinedTag:0xA432":["28\/1","75\/1","0\/0","0\/0"],"UndefinedTag:0xA434":"28-75mm","UndefinedTag:0xA435":0}}}},"item":{"id":1138,"url":"http:\/\/publications.newberry.org\/transcription\/mms-transcribe\/api\/items\/1138","resource":"items"},"element_texts":[],"extended_resources":[]},{"id":79954,"url":"http:\/\/publications.newberry.org\/transcription\/mms-transcribe\/api\/files\/79954","file_urls":{"original":"http:\/\/publications.newberry.org\/transcription\/mms-transcribe\/files\/original\/ef26c90f165083a736a0da4c8710235b.jpg","fullsize":"http:\/\/publications.newberry.org\/transcription\/mms-transcribe\/files\/fullsize\/ef26c90f165083a736a0da4c8710235b.jpg","thumbnail":"http:\/\/publications.newberry.org\/transcription\/mms-transcribe\/files\/thumbnails\/ef26c90f165083a736a0da4c8710235b.jpg","square_thumbnail":"http:\/\/publications.newberry.org\/transcription\/mms-transcribe\/files\/square_thumbnails\/ef26c90f165083a736a0da4c8710235b.jpg"},"added":"2018-10-02T20:01:36+00:00","modified":"2019-09-24T15:38:12+00:00","filename":"ef26c90f165083a736a0da4c8710235b.jpg","authentication":"2ec917e62527c016eecc1a8e4023c8cb","has_derivative_image":true,"mime_type":"image\/jpeg","order":null,"original_filename":"dance_ms_olson_box_01_fl_005_002_002_o2.jpg","size":1418063,"stored":true,"type_os":"JPEG image data, JFIF standard 1.01","metadata":{"mime_type":"image\/jpeg","video":{"dataformat":"jpg","lossless":false,"bits_per_sample":24,"pixel_aspect_ratio":1,"resolution_x":2879,"resolution_y":3600,"compression_ratio":0.045606852945339},"comments":{"IPTCEnvelope":{"CodedCharacterSet":["\u001b%G"]},"IPTCApplication":{"ApplicationRecordVersion":["\u0004"],"DateCreated":["20161018"],"TimeCreated":["030227"],"CopyrightNotice":["The Newberry Library"]}},"comments_html":{"IPTCEnvelope":{"CodedCharacterSet":["\u001b%G"]},"IPTCApplication":{"ApplicationRecordVersion":["\u0004"],"DateCreated":["20161018"],"TimeCreated":["030227"],"CopyrightNotice":["The Newberry Library"]}},"iptc":{"comments":{"IPTCEnvelope":{"CodedCharacterSet":["\u001b%G"]},"IPTCApplication":{"ApplicationRecordVersion":["\u0000\u0004"],"DateCreated":["20161018"],"TimeCreated":["030227"],"CopyrightNotice":["The Newberry Library"]}},"encoding":"ISO-8859-1"},"jpg":{"exif":{"FILE":{"FileName":"ef26c90f165083a736a0da4c8710235b.jpg","FileDateTime":1538510492,"FileSize":1418063,"FileType":2,"MimeType":"image\/jpeg","SectionsFound":"ANY_TAG, IFD0, EXIF"},"COMPUTED":{"html":"width=\"2879\" height=\"3600\"","Height":3600,"Width":2879,"IsColor":1,"ByteOrderMotorola":0,"CCDWidth":"21mm","ApertureFNumber":"f\/7.1"},"IFD0":{"Make":"Canon","Model":"Canon EOS 5D Mark III","Software":"Adobe Photoshop CS6 (Windows)","DateTime":"2016:10:18 15:58:59","Exif_IFD_Pointer":152},"EXIF":{"ExposureTime":0.02,"FNumber":7.1,"ExposureProgram":1,"ISOSpeedRatings":400,"UndefinedTag:0x8830":2,"UndefinedTag:0x8832":400,"ExifVersion":230,"DateTimeOriginal":"2016:10:18 03:02:27","DateTimeDigitized":"2016:10:18 03:02:27","ShutterSpeedValue":5.643856,"ApertureValue":5.655638,"ExposureBiasValue":0,"MaxApertureValue":3,"MeteringMode":5,"Flash":16,"FocalLength":38,"SubSecTimeOriginal":99,"ColorSpace":65535,"ExifImageWidth":3403,"ExifImageLength":4255,"FocalPlaneXResolution":1600,"FocalPlaneYResolution":1600,"FocalPlaneResolutionUnit":3,"CustomRendered":0,"ExposureMode":1,"WhiteBalance":1,"SceneCaptureType":0,"UndefinedTag:0xA431":358023000687,"UndefinedTag:0xA432":["28\/1","75\/1","0\/0","0\/0"],"UndefinedTag:0xA434":"28-75mm","UndefinedTag:0xA435":0}}}},"item":{"id":1138,"url":"http:\/\/publications.newberry.org\/transcription\/mms-transcribe\/api\/items\/1138","resource":"items"},"element_texts":[],"extended_resources":[]},{"id":79955,"url":"http:\/\/publications.newberry.org\/transcription\/mms-transcribe\/api\/files\/79955","file_urls":{"original":"http:\/\/publications.newberry.org\/transcription\/mms-transcribe\/files\/original\/cf3fc5617c73094aa6833c43b08c2449.jpg","fullsize":"http:\/\/publications.newberry.org\/transcription\/mms-transcribe\/files\/fullsize\/cf3fc5617c73094aa6833c43b08c2449.jpg","thumbnail":"http:\/\/publications.newberry.org\/transcription\/mms-transcribe\/files\/thumbnails\/cf3fc5617c73094aa6833c43b08c2449.jpg","square_thumbnail":"http:\/\/publications.newberry.org\/transcription\/mms-transcribe\/files\/square_thumbnails\/cf3fc5617c73094aa6833c43b08c2449.jpg"},"added":"2018-10-02T20:01:37+00:00","modified":"2019-09-24T15:38:12+00:00","filename":"cf3fc5617c73094aa6833c43b08c2449.jpg","authentication":"f8a7dcdd4a8a8b239f803f29d855d317","has_derivative_image":true,"mime_type":"image\/jpeg","order":null,"original_filename":"dance_ms_olson_box_01_fl_006_001_001_o2.jpg","size":1257041,"stored":true,"type_os":"JPEG image data, JFIF standard 1.01","metadata":{"mime_type":"image\/jpeg","video":{"dataformat":"jpg","lossless":false,"bits_per_sample":24,"pixel_aspect_ratio":1,"resolution_x":3600,"resolution_y":2895,"compression_ratio":0.040204727179684},"comments":{"IPTCEnvelope":{"CodedCharacterSet":["\u001b%G"]},"IPTCApplication":{"ApplicationRecordVersion":["\u0004"],"DateCreated":["20161018"],"TimeCreated":["024911"],"CopyrightNotice":["The Newberry Library"]}},"comments_html":{"IPTCEnvelope":{"CodedCharacterSet":["\u001b%G"]},"IPTCApplication":{"ApplicationRecordVersion":["\u0004"],"DateCreated":["20161018"],"TimeCreated":["024911"],"CopyrightNotice":["The Newberry Library"]}},"iptc":{"comments":{"IPTCEnvelope":{"CodedCharacterSet":["\u001b%G"]},"IPTCApplication":{"ApplicationRecordVersion":["\u0000\u0004"],"DateCreated":["20161018"],"TimeCreated":["024911"],"CopyrightNotice":["The Newberry Library"]}},"encoding":"ISO-8859-1"},"jpg":{"exif":{"FILE":{"FileName":"cf3fc5617c73094aa6833c43b08c2449.jpg","FileDateTime":1538510492,"FileSize":1257041,"FileType":2,"MimeType":"image\/jpeg","SectionsFound":"ANY_TAG, IFD0, EXIF"},"COMPUTED":{"html":"width=\"3600\" height=\"2895\"","Height":2895,"Width":3600,"IsColor":1,"ByteOrderMotorola":0,"CCDWidth":"26mm","ApertureFNumber":"f\/7.1"},"IFD0":{"Make":"Canon","Model":"Canon EOS 5D Mark III","Software":"Adobe Photoshop CS6 (Windows)","DateTime":"2016:10:18 15:56:03","Exif_IFD_Pointer":152},"EXIF":{"ExposureTime":0.02,"FNumber":7.1,"ExposureProgram":1,"ISOSpeedRatings":400,"UndefinedTag:0x8830":2,"UndefinedTag:0x8832":400,"ExifVersion":230,"DateTimeOriginal":"2016:10:18 02:49:11","DateTimeDigitized":"2016:10:18 02:49:11","ShutterSpeedValue":5.643856,"ApertureValue":5.655638,"ExposureBiasValue":0,"MaxApertureValue":3,"MeteringMode":5,"Flash":16,"FocalLength":42,"ColorSpace":65535,"ExifImageWidth":4276,"ExifImageLength":3439,"FocalPlaneXResolution":1600,"FocalPlaneYResolution":1600,"FocalPlaneResolutionUnit":3,"CustomRendered":0,"ExposureMode":1,"WhiteBalance":1,"SceneCaptureType":0,"UndefinedTag:0xA431":358023000687,"UndefinedTag:0xA432":["28\/1","75\/1","0\/0","0\/0"],"UndefinedTag:0xA434":"28-75mm","UndefinedTag:0xA435":0}}}},"item":{"id":1138,"url":"http:\/\/publications.newberry.org\/transcription\/mms-transcribe\/api\/items\/1138","resource":"items"},"element_texts":[],"extended_resources":[]},{"id":79956,"url":"http:\/\/publications.newberry.org\/transcription\/mms-transcribe\/api\/files\/79956","file_urls":{"original":"http:\/\/publications.newberry.org\/transcription\/mms-transcribe\/files\/original\/b916b647a4bce3c5f2233a10b658bad7.jpg","fullsize":"http:\/\/publications.newberry.org\/transcription\/mms-transcribe\/files\/fullsize\/b916b647a4bce3c5f2233a10b658bad7.jpg","thumbnail":"http:\/\/publications.newberry.org\/transcription\/mms-transcribe\/files\/thumbnails\/b916b647a4bce3c5f2233a10b658bad7.jpg","square_thumbnail":"http:\/\/publications.newberry.org\/transcription\/mms-transcribe\/files\/square_thumbnails\/b916b647a4bce3c5f2233a10b658bad7.jpg"},"added":"2018-10-02T20:01:38+00:00","modified":"2019-09-24T15:38:12+00:00","filename":"b916b647a4bce3c5f2233a10b658bad7.jpg","authentication":"355e3908fab0c7f20bc84245c3c7fcfe","has_derivative_image":true,"mime_type":"image\/jpeg","order":null,"original_filename":"dance_ms_olson_box_01_fl_006_001_002_o2.jpg","size":1100935,"stored":true,"type_os":"JPEG image data, JFIF standard 1.01","metadata":{"mime_type":"image\/jpeg","video":{"dataformat":"jpg","lossless":false,"bits_per_sample":24,"pixel_aspect_ratio":1,"resolution_x":3600,"resolution_y":2861,"compression_ratio":0.035630348104133},"comments":{"IPTCEnvelope":{"CodedCharacterSet":["\u001b%G"]},"IPTCApplication":{"ApplicationRecordVersion":["\u0004"],"DateCreated":["20161018"],"TimeCreated":["024915"],"CopyrightNotice":["The Newberry Library"]}},"comments_html":{"IPTCEnvelope":{"CodedCharacterSet":["\u001b%G"]},"IPTCApplication":{"ApplicationRecordVersion":["\u0004"],"DateCreated":["20161018"],"TimeCreated":["024915"],"CopyrightNotice":["The Newberry Library"]}},"iptc":{"comments":{"IPTCEnvelope":{"CodedCharacterSet":["\u001b%G"]},"IPTCApplication":{"ApplicationRecordVersion":["\u0000\u0004"],"DateCreated":["20161018"],"TimeCreated":["024915"],"CopyrightNotice":["The Newberry Library"]}},"encoding":"ISO-8859-1"},"jpg":{"exif":{"FILE":{"FileName":"b916b647a4bce3c5f2233a10b658bad7.jpg","FileDateTime":1538510492,"FileSize":1100935,"FileType":2,"MimeType":"image\/jpeg","SectionsFound":"ANY_TAG, IFD0, EXIF"},"COMPUTED":{"html":"width=\"3600\" height=\"2861\"","Height":2861,"Width":3600,"IsColor":1,"ByteOrderMotorola":0,"CCDWidth":"26mm","ApertureFNumber":"f\/7.1"},"IFD0":{"Make":"Canon","Model":"Canon EOS 5D Mark III","Software":"Adobe Photoshop CS6 (Windows)","DateTime":"2016:10:18 15:54:33","Exif_IFD_Pointer":152},"EXIF":{"ExposureTime":0.02,"FNumber":7.1,"ExposureProgram":1,"ISOSpeedRatings":400,"UndefinedTag:0x8830":2,"UndefinedTag:0x8832":400,"ExifVersion":230,"DateTimeOriginal":"2016:10:18 02:49:15","DateTimeDigitized":"2016:10:18 02:49:15","ShutterSpeedValue":5.643856,"ApertureValue":5.655638,"ExposureBiasValue":0,"MaxApertureValue":3,"MeteringMode":5,"Flash":16,"FocalLength":42,"SubSecTimeOriginal":91,"ColorSpace":65535,"ExifImageWidth":4230,"ExifImageLength":3362,"FocalPlaneXResolution":1600,"FocalPlaneYResolution":1600,"FocalPlaneResolutionUnit":3,"CustomRendered":0,"ExposureMode":1,"WhiteBalance":1,"SceneCaptureType":0,"UndefinedTag:0xA431":358023000687,"UndefinedTag:0xA432":["28\/1","75\/1","0\/0","0\/0"],"UndefinedTag:0xA434":"28-75mm","UndefinedTag:0xA435":0}}}},"item":{"id":1138,"url":"http:\/\/publications.newberry.org\/transcription\/mms-transcribe\/api\/items\/1138","resource":"items"},"element_texts":[],"extended_resources":[]}]